{
    "280": {
        "neg": {
            "exc": {
                "norad": {
                    "normfac": 13728300.0
                }
            },
            "inc": {
                "norad": {
                    "normfac": 131572000000.0
                },
                "rad": {
                    "normfac": 132123000000.0
                }
            }
        },
        "pos": {
            "exc": {
                "norad": {
                    "normfac": 13975400.0
                }
            },
            "inc": {
                "norad": {
                    "normfac": 131572000000.0
                },
                "rad": {
                    "normfac": 132123000000.0
                }
            }
        }
    }
}
