{
    "300": {
        "neg": {
            "D2": {
                "delta": {
                    "normfac": 19308800.0
                },
                "exc": {
                    "rad": {
                        "normfac": 20683100.0
                    }
                },
                "inc": {
                    "norad": {
                        "normfac": 88845900000.0
                    },
                    "rad": {
                        "normfac": 95808100000.0
                    }
                },
                "rho": {
                    "normfac": 880075000.0
                }
            }
        },
        "pos": {
            "D2": {
                "delta": {
                    "normfac": 19308800.0
                },
                "exc": {
                    "rad": {
                        "normfac": 20672100.0
                    }
                },
                "inc": {
                    "norad": {
                        "normfac": 88845900000.0
                    },
                    "rad": {
                        "normfac": 95808100000.0
                    }
                },
                "rho": {
                    "normfac": 880075000.0
                }
            }
        }
    }
}
