{
    "300": {
        "neg": {
            "D2": {
                "delta": {
                    "normfac": 31593100.0
                },
                "inc": {
                    "norad": {
                        "normfac": 88638100000.0
                    },
                    "rad": {
                        "normfac": 129219000000.0
                    }
                }
            }
        },
        "pos": {
            "D2": {
                "delta": {
                    "normfac": 31593100.0
                },
                "inc": {
                    "norad": {
                        "normfac": 88638100000.0
                    },
                    "rad": {
                        "normfac": 129219000000.0
                    }
                }
            }
        }
    }
}
